proxys/__init__.py
proxys/api.py
proxys/base_proxy.py
proxys/proxys.txt
proxys/__pycache__/__init__.cpython-39.pyc
proxys/__pycache__/api.cpython-39.pyc
proxys/__pycache__/base_proxy.cpython-39.pyc
proxys-0.0.4.dist-info/METADATA
proxys-0.0.4.dist-info/WHEEL
proxys-0.0.4.dist-info/top_level.txt
proxys-0.0.4.dist-info/RECORD
