Metadata-Version: 2.1
Name: proxys
Version: 0.0.4
Summary: get free proxy regularly peer 10 minutes
Home-page: https://github.com/zuoxiaolei/proxys
Author: zuoxiaolei
Author-email: 1905561110@qq.com
License: Apache 2.0
Project-URL: Documentation, https://github.com/zuoxiaolei/proxys
Project-URL: Source, https://github.com/zuoxiaolei/proxys
Keywords: proxy
Platform: any
Requires-Python: >=3
Requires-Dist: html5lib (>=1.1)
Requires-Dist: requests
Requires-Dist: beautifulsoup4
Requires-Dist: tqdm
Requires-Dist: retrying
